route/__init__.py
route/dir.py
route/directory_tree.py
route/emoji.py
route/generate_get_dir_prefix.py
route/markdownify.py
route/setup_utils.py
route/starts_with.py
route-2025.2.23.1.dist-info/METADATA
route-2025.2.23.1.dist-info/WHEEL
route-2025.2.23.1.dist-info/top_level.txt
route-2025.2.23.1.dist-info/RECORD
